cobra/__init__.py
cobra/exceptions.py
cobra/core/__init__.py
cobra/core/configuration.py
cobra/core/dictlist.py
cobra/core/formula.py
cobra/core/gene.py
cobra/core/group.py
cobra/core/metabolite.py
cobra/core/model.py
cobra/core/object.py
cobra/core/reaction.py
cobra/core/singleton.py
cobra/core/solution.py
cobra/core/species.py
cobra/data/__init__.py
cobra/data/iJO1366.xml.gz
cobra/data/mini.json
cobra/data/mini.mat
cobra/data/mini.yml
cobra/data/mini_cobra.xml
cobra/data/salmonella.xml.gz
cobra/data/textbook.xml.gz
cobra/flux_analysis/__init__.py
cobra/flux_analysis/deletion.py
cobra/flux_analysis/fastcc.py
cobra/flux_analysis/gapfilling.py
cobra/flux_analysis/geometric.py
cobra/flux_analysis/helpers.py
cobra/flux_analysis/loopless.py
cobra/flux_analysis/moma.py
cobra/flux_analysis/parsimonious.py
cobra/flux_analysis/phenotype_phase_plane.py
cobra/flux_analysis/reaction.py
cobra/flux_analysis/room.py
cobra/flux_analysis/variability.py
cobra/io/__init__.py
cobra/io/dict.py
cobra/io/json.py
cobra/io/mat.py
cobra/io/sbml.py
cobra/io/schema_v1.json
cobra/io/yaml.py
cobra/io/web/__init__.py
cobra/io/web/abstract_model_repository.py
cobra/io/web/bigg_models_repository.py
cobra/io/web/biomodels_repository.py
cobra/io/web/cobrapy_repository.py
cobra/io/web/load.py
cobra/manipulation/__init__.py
cobra/manipulation/annotate.py
cobra/manipulation/delete.py
cobra/manipulation/modify.py
cobra/manipulation/validate.py
cobra/medium/__init__.py
cobra/medium/annotations.py
cobra/medium/boundary_types.py
cobra/medium/minimal_medium.py
cobra/sampling/__init__.py
cobra/sampling/achr.py
cobra/sampling/core.py
cobra/sampling/hr_sampler.py
cobra/sampling/optgp.py
cobra/sampling/sampling.py
cobra/summary/__init__.py
cobra/summary/metabolite_summary.py
cobra/summary/model_summary.py
cobra/summary/reaction_summary.py
cobra/summary/summary.py
cobra/util/__init__.py
cobra/util/array.py
cobra/util/context.py
cobra/util/process_pool.py
cobra/util/solver.py
cobra/util/util.py
cobra-0.30.0.dist-info/licenses/LICENSE
cobra-0.30.0.dist-info/METADATA
cobra-0.30.0.dist-info/WHEEL
cobra-0.30.0.dist-info/top_level.txt
cobra-0.30.0.dist-info/zip-safe
cobra-0.30.0.dist-info/RECORD
