Metadata-Version: 2.4
Name: cobra
Version: 0.30.0
Summary: COBRApy is a package for constraint-based modeling of metabolic networks.
Home-page: https://opencobra.github.io/cobrapy
Download-URL: https://pypi.org/project/cobra
Author: The cobrapy core development team.
Author-email: cobra-pie@googlegroups.com
Maintainer: Moritz E. Beber
Maintainer-email: moritz.beber@gmail.com
License: LGPL-2.0-or-later OR GPL-2.0-or-later
Project-URL: Source Code, https://github.com/opencobra/cobrapy
Project-URL: Documentation, https://cobrapy.readthedocs.io
Project-URL: Bug Tracker, https://github.com/opencobra/cobrapy/issues
Keywords: metabolism,biology,constraint-based,linear programming,mixed-integer,optimization,flux-balance analysis,reconstruction
Classifier: Development Status :: 5 - Production/Stable
Classifier: Intended Audience :: Science/Research
Classifier: License :: OSI Approved :: GNU General Public License v2 or later (GPLv2+)
Classifier: License :: OSI Approved :: GNU Lesser General Public License v2 or later (LGPLv2+)
Classifier: Natural Language :: English
Classifier: Operating System :: OS Independent
Classifier: Programming Language :: Python :: 3.8
Classifier: Programming Language :: Python :: 3.9
Classifier: Programming Language :: Python :: 3.10
Classifier: Programming Language :: Python :: 3.11
Classifier: Programming Language :: Python :: Implementation :: CPython
Classifier: Topic :: Scientific/Engineering :: Bio-Informatics
License-File: LICENSE
Requires-Dist: appdirs~=1.4
Requires-Dist: depinfo~=2.2
Requires-Dist: diskcache~=5.0
Requires-Dist: future
Requires-Dist: httpx~=0.24
Requires-Dist: numpy>=1.13
Requires-Dist: optlang~=1.8
Requires-Dist: pandas<3.0,>=1.0
Requires-Dist: pydantic>=1.6
Requires-Dist: python-libsbml~=5.19
Requires-Dist: rich>=8.0
Requires-Dist: ruamel.yaml~=0.16
Requires-Dist: swiglpk
Provides-Extra: array
Requires-Dist: scipy; extra == "array"
Provides-Extra: development
Requires-Dist: black; extra == "development"
Requires-Dist: bumpversion; extra == "development"
Requires-Dist: isort; extra == "development"
Requires-Dist: tox; extra == "development"
Dynamic: download-url
Dynamic: license-file
